README.rst
setup.cfg
setup.py
pyttsx3/__init__.py
pyttsx3/driver.py
pyttsx3/engine.py
pyttsx3/six.py
pyttsx3/voice.py
pyttsx3/drivers/__init__.py
pyttsx3/drivers/_espeak.py
pyttsx3/drivers/dummy.py
pyttsx3/drivers/espeak.py
pyttsx3/drivers/nsss.py
pyttsx3/drivers/sapi5.py
pyttsx3eaidk.egg-info/PKG-INFO
pyttsx3eaidk.egg-info/SOURCES.txt
pyttsx3eaidk.egg-info/dependency_links.txt
pyttsx3eaidk.egg-info/requires.txt
pyttsx3eaidk.egg-info/top_level.txt