Metadata-Version: 1.1
Name: pyttsx3eaidk
Version: 2.91
Summary: Text to Speech (TTS) library for Python 3. Works without internet connection or delay. Supports multiple TTS engines, including Sapi5, nsss, and espeak.
Home-page: https://github.com/nateshmbhat/pyttsx3
Author: Natesh M Bhat
Author-email: nateshmbhatofficial@gmail.com
License: UNKNOWN
Keywords: pyttsx,ivona,pyttsx for python3,TTS for python3,pyttsx3,text to speech for python,tts,text to speech,speech,speech synthesis,offline text to speech,offline tts,gtts
Platform: UNKNOWN
Classifier: Intended Audience :: End Users/Desktop
Classifier: Intended Audience :: Developers
Classifier: Intended Audience :: Information Technology
Classifier: Intended Audience :: System Administrators
Classifier: Operating System :: MacOS :: MacOS X
Classifier: Operating System :: Microsoft :: Windows
Classifier: Operating System :: POSIX
Classifier: License :: OSI Approved :: GNU General Public License v3 (GPLv3)
Classifier: Programming Language :: Python :: 3
Classifier: Programming Language :: Python :: 3.5
Classifier: Programming Language :: Python :: 3.6
Classifier: Programming Language :: Python :: 3.7
